printkit/BackgroundKit.py
printkit/ColorKit.py
printkit/TextKit.py
printkit/__init__.py
printkit-0.1.3.dist-info/LICENSE
printkit-0.1.3.dist-info/METADATA
printkit-0.1.3.dist-info/WHEEL
printkit-0.1.3.dist-info/top_level.txt
printkit-0.1.3.dist-info/RECORD
