Metadata-Version: 2.1
Name: printkit
Version: 0.1.3
Summary: Printkit is an easy to use python package which contains various tools that enable you to have a distinct and good looking outputs.
Home-page: https://github.com/CipherKill/printkit
Author: CipherKill
Author-email: alanraju99@gmail.com
License: MIT
Keywords: python,print,terminal,console,colors,style
Platform: UNKNOWN
Classifier: Development Status :: 4 - Beta
Classifier: Intended Audience :: Developers
Classifier: Programming Language :: Python :: 3
Classifier: Operating System :: Unix
Classifier: Operating System :: MacOS :: MacOS X
Classifier: Operating System :: Microsoft :: Windows
License-File: LICENSE
